nmatheg/__init__.py
nmatheg/configs.py
nmatheg/dataset.py
nmatheg/datasets.ini
nmatheg/models.py
nmatheg/ner_utils.py
nmatheg/nmatheg.py
nmatheg/preprocess_ner.py
nmatheg/preprocess_qa.py
nmatheg/qa_utils.py
nmatheg/tests.py
nmatheg/utils.py
nmatheg-0.0.4.dist-info/METADATA
nmatheg-0.0.4.dist-info/WHEEL
nmatheg-0.0.4.dist-info/top_level.txt
nmatheg-0.0.4.dist-info/RECORD
