Metadata-Version: 2.1
Name: nmatheg
Version: 0.0.4
Summary: UNKNOWN
Home-page: UNKNOWN
Author: Zaid Alyafeai, Maged Saeed
Author-email: arabicmachinelearning@gmail.com
License: MIT
Platform: UNKNOWN
Requires-Python: >=3.6
Requires-Dist: tnkeeh
Requires-Dist: tkseem
Requires-Dist: tfds-nightly
Requires-Dist: datasets
Requires-Dist: transformers
Requires-Dist: accelerate
Requires-Dist: seqeval
